snap_saas_base/__init__.py
snap_saas_base/models/__init__.py
snap_saas_base/models/base_model.py
snap_saas_base/models/chat.py
snap_saas_base/models/organization.py
snap_saas_base/models/user.py
snap_saas_base/models/workspace.py
snap_saas_base/py.typed
snap_saas_base/schemas/__init__.py
snap_saas_base/schemas/user.py
snap_saas_base-0.10.2.dist-info/METADATA
snap_saas_base-0.10.2.dist-info/WHEEL
snap_saas_base-0.10.2.dist-info/RECORD
