Metadata-Version: 2.1
Name: snap-saas-base
Version: 0.10.2
Summary: Snap Env (https://snapenv.com) Python base module.
Home-page: https://github.com/orgs/snapenv/snap-saas-base
Author: Abner G Jacobsen
Author-email: abner@apoana.com.br
Requires-Python: >=3.11,<4.0
Classifier: Programming Language :: Python :: 3
Classifier: Programming Language :: Python :: 3.11
Classifier: Programming Language :: Python :: 3.12
Requires-Dist: pydantic[email] (>=2.3.0,<3.0.0)
Requires-Dist: sqlalchemy[asyncio] (>=2.0.18,<3.0.0)
Requires-Dist: uuid6 (>=2023.5.2,<2024.0.0)
Project-URL: Repository, https://github.com/orgs/snapenv/snap-saas-base
